CHANGELOG.md
README.md
VERSION
pettifogger/__init__.py
pettifogger/checks/__init__.py
pettifogger/checks/jobs_checkout_test.py
pettifogger/checks/jobs_env_variables_test.py
pettifogger/checks/jobs_needs_test.py
pettifogger/checks/root_schema_test.py
pettifogger/checks/testdata/jobs/circular_needs.yml
pettifogger/checks/testdata/jobs/command_env_var.yml
pettifogger/checks/testdata/jobs/export_env_var.yml
pettifogger/checks/testdata/jobs/has_checkout.yml
pettifogger/checks/testdata/jobs/missing_env_vars.yml
pettifogger/checks/testdata/jobs/missing_needs.yml
pettifogger/checks/testdata/jobs/no_checkout.yml
pettifogger/checks/testdata/jobs/runtime_env_var.yml
pettifogger/checks/testdata/schema/missing_jobs.yml
pettifogger/checks/testdata/schema/missing_triggers.yml
pettifogger/checks/validation_tests.py
pettifogger/main.py
pettifogger/testdata/.github/workflows/broken_yaml.yml
pettifogger/testdata/.github/workflows/example.yml
pettifogger/testdata/.github/workflows/missing_triggers.yml
pettifogger/testdata/.github/workflows/output_id_var_not_defined_in_steps.yml
pettifogger/testdata/.github/workflows/valid.yml
pettifogger/testdata/.github/workflows/weird_need_with_if.yml
pettifogger/utils/__init__.py
pettifogger/utils/configuration.py
pettifogger/utils/constants.py
pettifogger/utils/schema.json
pettifogger/utils/stateful_logger.py
pettifogger/utils/yaml.py
pettifogger/workflow/__init__.py
pettifogger/workflow/structure/__init__.py
pettifogger/workflow/structure/defaults.py
pettifogger/workflow/structure/env.py
pettifogger/workflow/structure/jobs/__init__.py
pettifogger/workflow/structure/jobs/container.py
pettifogger/workflow/structure/jobs/job.py
pettifogger/workflow/structure/jobs/step.py
pettifogger/workflow/structure/jobs/strategy.py
pettifogger/workflow/structure/on.py
pettifogger/workflow/structure/root.py
pettifogger-0.5.0.dist-info/entry_points.txt
pettifogger-0.5.0.dist-info/LICENSE
pettifogger-0.5.0.dist-info/WHEEL
pettifogger-0.5.0.dist-info/METADATA
pettifogger-0.5.0.dist-info/RECORD
